sand/__init__.py
sand/__main__.py
sand/calibration/__init__.py
sand/calibration/classes/__init__.py
sand/calibration/classes/camera.py
sand/calibration/classes/lidar.py
sand/calibration/classes/map.py
sand/calibration/classes/state.py
sand/calibration/generate_calibration_image.py
sand/calibration/helper/__init__.py
sand/calibration/helper/calibration.py
sand/calibration/helper/config.py
sand/calibration/helper/image.py
sand/calibration/helper/lidar.py
sand/calibration/helper/transformation.py
sand/calibration/image_calibration.py
sand/calibration/image_download.py
sand/calibration/image_focal.py
sand/calibration/map_calibration.py
sand/cli/__init__.py
sand/cli/arguments.py
sand/cli/parser.py
sand/cli/starter.py
sand/cli/system.py
sand/config/__init__.py
sand/config/config.py
sand/config/helpers.py
sand/config/transformer_combination_config.py
sand/converter/__init__.py
sand/converter/convert.py
sand/converter/pipeline/__init__.py
sand/converter/pipeline/converter.py
sand/datatypes/__init__.py
sand/datatypes/aerialmap.py
sand/datatypes/datapoint.py
sand/datatypes/delta.py
sand/datatypes/frame.py
sand/datatypes/packet.py
sand/datatypes/types.py
sand/definition/__init__.py
sand/definition/system_definition.py
sand/interfaces/__init__.py
sand/interfaces/communication/__init__.py
sand/interfaces/communication/communicator.py
sand/interfaces/communication/mqtt_util.py
sand/interfaces/config/__init__.py
sand/interfaces/config/configuration_management.py
sand/interfaces/shutdown/__init__.py
sand/interfaces/shutdown/shutdown_able.py
sand/interfaces/synchronization/__init__.py
sand/interfaces/synchronization/isolator.py
sand/interfaces/synchronization/node.py
sand/interfaces/util/__init__.py
sand/interfaces/util/collectable.py
sand/interfaces/util/subscriber.py
sand/logger/__init__.py
sand/logger/initialize.py
sand/logger/logger.py
sand/logger/mqtt_logger.py
sand/main/__init__.py
sand/main/main.py
sand/map/__init__.py
sand/map/build.py
sand/map/pipeline/__init__.py
python_sand-1.1.1.dist-info/entry_points.txt
python_sand-1.1.1.dist-info/LICENSE
python_sand-1.1.1.dist-info/WHEEL
python_sand-1.1.1.dist-info/METADATA
python_sand-1.1.1.dist-info/RECORD
