Metadata-Version: 2.1
Name: python-sand
Version: 1.1.1
Summary: Processing sensor and video data made easy
Home-page: https://gitlab.com/sand7/sand
License: MIT
Author: Moritz Sauter
Author-email: sauter@synyx.de
Maintainer: Moritz Sauter
Maintainer-email: sauter@synyx.de
Requires-Python: >=3.8,<3.9
Classifier: Development Status :: 5 - Production/Stable
Classifier: Environment :: GPU
Classifier: Intended Audience :: Developers
Classifier: License :: OSI Approved :: MIT License
Classifier: Natural Language :: English
Classifier: Natural Language :: German
Classifier: Operating System :: POSIX :: Linux
Classifier: Programming Language :: Python :: 3
Classifier: Programming Language :: Python :: 3.8
Classifier: Topic :: Multimedia :: Video :: Capture
Classifier: Topic :: Multimedia :: Video :: Conversion
Classifier: Topic :: Multimedia :: Video :: Display
Classifier: Topic :: Scientific/Engineering :: Artificial Intelligence
Classifier: Topic :: Software Development :: Libraries :: Python Modules
Classifier: Typing :: Typed
Provides-Extra: full
Provides-Extra: metric
Provides-Extra: neural_base
Provides-Extra: neural_full
Provides-Extra: neural_mmdet
Provides-Extra: neural_yolox
Provides-Extra: publisher
Requires-Dist: eventlet (>=0.33.1,<0.34.0); extra == "publisher" or extra == "full"
Requires-Dist: flask (>=2.1.2,<3.0.0); extra == "publisher" or extra == "full"
Requires-Dist: flask-socketio (>=5.2.0,<6.0.0); extra == "publisher" or extra == "full"
Requires-Dist: influxdb-client (>=1.30.0,<2.0.0); extra == "metric" or extra == "full"
Requires-Dist: mlcvzoo-base (>=3.2.1,<4.0.0); extra == "neural_base" or extra == "neural_yolox" or extra == "neural_mmdet" or extra == "neural_full" or extra == "full"
Requires-Dist: mlcvzoo-mmdetection (>=3.0.1,<4.0.0); extra == "neural_mmdet" or extra == "neural_full" or extra == "full"
Requires-Dist: mlcvzoo-yolox (>=4.0.2,<5.0.0); extra == "neural_yolox" or extra == "neural_full" or extra == "full"
Requires-Dist: nptyping (>=2.2.0,<3.0.0)
Requires-Dist: numpy (>=1.21.4,<2.0.0)
Requires-Dist: opencv-contrib-python (>=4.5,<4.6)
Requires-Dist: overrides (>=6.1.0,<7.0.0)
Requires-Dist: paho-mqtt (>=1.6.1,<2.0.0)
Requires-Dist: python-prctl (>=1.8.1,<2.0.0)
Requires-Dist: yaml-config-builder (>=6.0.0,<7.0.0)
Project-URL: Documentation, https://gitlab.com/sand7/sand/-/tree/main/doc
Project-URL: Repository, https://gitlab.com/sand7/sand
